hienoi/__init__.py
hienoi/_common.py
hienoi/_dynamicarray.py
hienoi/_kdtree.py
hienoi/_nani.py
hienoi/_numeric.py
hienoi/_orderedbuffer.py
hienoi/_vectors.py
hienoi/application.py
hienoi/dynamics.py
hienoi/gui.py
hienoi/renderer.py
hienoi/shaders/grid.frag
hienoi/shaders/grid.vert
hienoi/shaders/particles.frag
hienoi/shaders/particles.vert
hienoi/shaders/point_particles.frag
hienoi/shaders/point_particles.vert
hienoi-0.2.0.dist-info/DESCRIPTION.rst
hienoi-0.2.0.dist-info/LICENSE.txt
hienoi-0.2.0.dist-info/METADATA
hienoi-0.2.0.dist-info/RECORD
hienoi-0.2.0.dist-info/WHEEL
hienoi-0.2.0.dist-info/metadata.json
hienoi-0.2.0.dist-info/top_level.txt
