Metadata-Version: 2.0
Name: hienoi
Version: 0.2.0
Summary: 2D particle playground
Home-page: https://github.com/christophercrouzet/hienoi
Author: Christopher Crouzet
Author-email: christopher.crouzet@gmail.com
License: MIT
Keywords: 2D particles OpenGL nani NumPy
Platform: UNKNOWN
Classifier: Development Status :: 4 - Beta
Classifier: Intended Audience :: Developers
Classifier: License :: OSI Approved :: MIT License
Classifier: Programming Language :: Python
Classifier: Programming Language :: Python :: 2
Classifier: Programming Language :: Python :: 2.7
Classifier: Programming Language :: Python :: 3
Classifier: Programming Language :: Python :: 3.4
Classifier: Programming Language :: Python :: 3.5
Classifier: Programming Language :: Python :: 3.6
Classifier: Topic :: Software Development :: Libraries :: Python Modules
Classifier: Topic :: Utilities
Requires-Dist: PyOpenGL
Requires-Dist: PySDL2
Requires-Dist: nani
Requires-Dist: numpy
Provides-Extra: dev
Requires-Dist: coverage; extra == 'dev'
Requires-Dist: tox; extra == 'dev'
